{
  "/_app": "pages/_app.js",
  "/_error": "pages/_error.js",
  "/administracion-salones": "pages/administracion-salones.html",
  "/administrar-solicitudes": "pages/administrar-solicitudes.html",
  "/conferencia-curso/[id]": "pages/conferencia-curso/[id].html",
  "/conferencias-pasadas": "pages/conferencias-pasadas.html",
  "/convalida-conferencia": "pages/convalida-conferencia.html",
  "/": "pages/index.html",
  "/iniciar-sesion": "pages/iniciar-sesion.html",
  "/mis-conferencias": "pages/mis-conferencias.html",
  "/olvidaste-contrasena": "pages/olvidaste-contrasena.html",
  "/perfil": "pages/perfil.html",
  "/proximas-conferencias": "pages/proximas-conferencias.html",
  "/registrarse": "pages/registrarse.html",
  "/relacion-conferencias": "pages/relacion-conferencias.html",
  "/repositorio": "pages/repositorio.html",
  "/restablecer-contrasena": "pages/restablecer-contrasena.html",
  "/solicitudes": "pages/solicitudes.html",
  "/sugiere-conferencia": "pages/sugiere-conferencia.html",
  "/solicitudes/solicitar-conferencia": "pages/solicitudes/solicitar-conferencia.html",
  "/usuario": "pages/usuario.html",
  "/_document": "pages/_document.js",
  "/404": "pages/404.html"
}